{
    "LabelTemplate": "ControlTemplate",
    "DocumentLabelTemplate": "ControlTemplate",
    "WindowTemplate": "ControlTemplate",
    "MenuTemplate": "WindowTemplate",
    "ButtonTemplate": "ControlTemplate",
    "SelectableButtonTemplate": "ButtonTemplate",
    "ToolstripButtonTemplate": "SelectableButtonTemplate",
    "ListViewColumnHeaderTemplate": "ToolstripButtonTemplate",
    "ComboBoxTemplate": "ToolstripButtonTemplate",
    "ScrollTemplate": "ControlTemplate",
    "ScrollViewTemplate": "ControlTemplate",
    "DocumentViewerTemplate": "ScrollViewTemplate",
    "ListControlTemplate": "ScrollViewTemplate",
    "TextListTemplate": "ListControlTemplate",
    "ListViewTemplate": "ListControlTemplate",
    "TreeViewTemplate": "ListControlTemplate",
    "TabTemplate": "ControlTemplate",
    "DatePickerTemplate": "ControlTemplate",
    "DateComboBoxTemplate": "ComboBoxTemplate",
    "RibbonTabTemplate": "TabTemplate",
    "RibbonGroupTemplate": "ControlTemplate",
    "RibbonIconLabelTemplate": "ControlTemplate",
    "RibbonButtonsTemplate": "ControlTemplate",
    "RibbonToolstripsTemplate": "ControlTemplate",
    "RibbonToolstripMenuTemplate": "MenuTemplate",
    "RibbonGalleryTemplate": "ControlTemplate",
    "RibbonGalleryListTemplate": "RibbonGalleryTemplate"
}